<?xml version="1.0" encoding="utf-8"?>
<!DOCTYPE hibernate-mapping PUBLIC "-//Hibernate/Hibernate Mapping DTD 3.0//EN"
"http://www.hibernate.org/dtd/hibernate-mapping-3.0.dtd">
<!-- 
    Mapping file autogenerated by MyEclipse Persistence Tools
-->
<hibernate-mapping>
    <class name="com.flying.xiao.bean.Friend" table="Friend" schema="dbo" catalog="Xiao">
        <id name="id" type="java.lang.Long">
            <column name="id" />
            <generator class="assigned" />
        </id>
        <many-to-one name="userInfoByUserId" class="com.flying.xiao.bean.UserInfo" fetch="select">
            <column name="user_id" />
        </many-to-one>
        <many-to-one name="userInfoByUserFriendBelongUserId" class="com.flying.xiao.bean.UserInfo" fetch="select">
            <column name="user_friend_belong_user_id" />
        </many-to-one>
    </class>
</hibernate-mapping>
